osmexp/__init__.py
osmexp/__main__.py
osmexp/fetcher.py
osmexp/geojson.py
osmexp-0.1.0.dist-info/LICENSE
osmexp-0.1.0.dist-info/METADATA
osmexp-0.1.0.dist-info/WHEEL
osmexp-0.1.0.dist-info/entry_points.txt
osmexp-0.1.0.dist-info/top_level.txt
osmexp-0.1.0.dist-info/RECORD
