Metadata-Version: 2.1
Name: osmexp
Version: 0.1.0
Summary: OpenStreetMap GeoJSON Exporter
Home-page: https://github.com/racum/osmexp
Author: Ronaldo Ferreira
Author-email: ronaldo@racum.com
License: BSD-3-Clause
Project-URL: Source, https://github.com/racum/osmexp
Classifier: Development Status :: 2 - Pre-Alpha
Classifier: Intended Audience :: Developers
Classifier: License :: OSI Approved :: BSD License
Classifier: Natural Language :: English
Classifier: Programming Language :: Python :: 3.11
Classifier: Programming Language :: Python :: 3.12
Requires-Python: >=3.11
License-File: LICENSE
Requires-Dist: requests
Requires-Dist: shapely
